shopee_affiliate/__init__.py
shopee_affiliate/_typing.py
shopee_affiliate/client.py
shopee_afflib-1.0.20.dist-info/licenses/LICENSE
shopee_afflib-1.0.20.dist-info/METADATA
shopee_afflib-1.0.20.dist-info/WHEEL
shopee_afflib-1.0.20.dist-info/top_level.txt
shopee_afflib-1.0.20.dist-info/RECORD
