Metadata-Version: 2.4
Name: shopee-afflib
Version: 1.0.20
Summary: Biblioteca para integração com a API de Afiliados da Shopee (síncrona e assíncrona).
Author-email: Anthony Santos <anthonyxda@live.com>
License: MIT
Project-URL: Homepage, https://github.com/anthonyxda/shopee-afflib
Project-URL: Source, https://github.com/anthonyxda/shopee-afflib
Requires-Python: >=3.8
License-File: LICENSE
Requires-Dist: requests>=2.0
Requires-Dist: aiohttp>=3.8
Dynamic: license-file
